gros_client_car/__init__.py
gros_client_car/car.py
gros_client_car-1.0.0.dist-info/LICENSE
gros_client_car-1.0.0.dist-info/METADATA
gros_client_car-1.0.0.dist-info/WHEEL
gros_client_car-1.0.0.dist-info/top_level.txt
gros_client_car-1.0.0.dist-info/RECORD
