Metadata-Version: 2.1
Name: gros-client-car
Version: 1.0.0
Summary: fourier car ctrl sdk
Home-page: https://github.com/FFTAI/gros_client_py/tree/feat-car/0721
Author: jax
Author-email: ming.li@fftai.com
License: MIT
Classifier: Programming Language :: Python :: 3
Classifier: License :: OSI Approved :: MIT License
Classifier: Operating System :: OS Independent
Requires-Python: >=3
License-File: LICENSE
Requires-Dist: requests >=2.31.0
Requires-Dist: websocket-client >=1.6.2
